Workbook

Sheet Grille tarifaire
A1: LIGUITA — Grille tarifaire détaillée (particuliers)
A2: Frais de mise en relation par classe d'objet — FCFA (XAF) · Version 2.1 — septembre 2026
A3: Calibrée sur les prix observés à N'Djamena (septembre 2026) — voir l'onglet « Calibrage marché ». Les tranches de valeur estimée sont indicatives. Règle : valeur déclarée > 1 000 000 FCFA → classe C5.
A4: Type d'objet | B4: Classe | C4: Valeur estimée indicative (FCFA) | D4: Frais de base (FCFA) | E4: Récompense trouveur (FCFA) | F4: Commission Liguita (FCFA) | G4: Part trouveur | H4: Remarques
A5: Carte d'identité, passeport, permis de conduire | B5: C1 | C5: 5 000 – 60 000 (remplacement officiel : CNI 10 000, permis 25 000, passeport 60 000) | D5: =IF($B5="C5", ROUND(MAX(Parametres!$B$12, MIN(Parametres!$B$13, Parametres!$B$11*1500000)), 0), VLOOKUP($B5,Parametres!$A$4:$C$8,2,0)) | E5: =IF($B5="C5", ROUND($D5*Parametres!$B$14,0), VLOOKUP($B5,Parametres!$A$4:$C$8,3,0)) | F5: =$D5-$E5 | G5: =$E5/$D5
A6: Carte d'étudiant / carte professionnelle | B6: C1 | C6: < 10 000 | D6: =IF($B6="C5", ROUND(MAX(Parametres!$B$12, MIN(Parametres!$B$13, Parametres!$B$11*1500000)), 0), VLOOKUP($B6,Parametres!$A$4:$C$8,2,0)) | E6: =IF($B6="C5", ROUND($D6*Parametres!$B$14,0), VLOOKUP($B6,Parametres!$A$4:$C$8,3,0)) | F6: =$D6-$E6 | G6: =$E6/$D6
A7: Diplôme, carnet de santé, documents administratifs | B7: C1 | C7: coût de duplication faible | D7: =IF($B7="C5", ROUND(MAX(Parametres!$B$12, MIN(Parametres!$B$13, Parametres!$B$11*1500000)), 0), VLOOKUP($B7,Parametres!$A$4:$C$8,2,0)) | E7: =IF($B7="C5", ROUND($D7*Parametres!$B$14,0), VLOOKUP($B7,Parametres!$A$4:$C$8,3,0)) | F7: =$D7-$E7 | G7: =$E7/$D7
A8: Jeu de clés (sans véhicule) | B8: C2 | C8: 2 000 – 5 000 (duplication, proxy régional) | D8: =IF($B8="C5", ROUND(MAX(Parametres!$B$12, MIN(Parametres!$B$13, Parametres!$B$11*1500000)), 0), VLOOKUP($B8,Parametres!$A$4:$C$8,2,0)) | E8: =IF($B8="C5", ROUND($D8*Parametres!$B$14,0), VLOOKUP($B8,Parametres!$A$4:$C$8,3,0)) | F8: =$D8-$E8 | G8: =$E8/$D8
A9: Portefeuille / sac à main (avec papiers) | B9: C2 | C9: 5 000 – 60 000 (contenu) | D9: =IF($B9="C5", ROUND(MAX(Parametres!$B$12, MIN(Parametres!$B$13, Parametres!$B$11*1500000)), 0), VLOOKUP($B9,Parametres!$A$4:$C$8,2,0)) | E9: =IF($B9="C5", ROUND($D9*Parametres!$B$14,0), VLOOKUP($B9,Parametres!$A$4:$C$8,3,0)) | F9: =$D9-$E9 | G9: =$E9/$D9
A10: Sac à dos, bagage de voyage | B10: C2 | C10: 10 000 – 80 000 | D10: =IF($B10="C5", ROUND(MAX(Parametres!$B$12, MIN(Parametres!$B$13, Parametres!$B$11*1500000)), 0), VLOOKUP($B10,Parametres!$A$4:$C$8,2,0)) | E10: =IF($B10="C5", ROUND($D10*Parametres!$B$14,0), VLOOKUP($B10,Parametres!$A$4:$C$8,3,0)) | F10: =$D10-$E10 | G10: =$E10/$D10 | H10: Article de marque → classe C4
A11: Lunettes | B11: C2 | C11: 10 000 – 60 000 | D11: =IF($B11="C5", ROUND(MAX(Parametres!$B$12, MIN(Parametres!$B$13, Parametres!$B$11*1500000)), 0), VLOOKUP($B11,Parametres!$A$4:$C$8,2,0)) | E11: =IF($B11="C5", ROUND($D11*Parametres!$B$14,0), VLOOKUP($B11,Parametres!$A$4:$C$8,3,0)) | F11: =$D11-$E11 | G11: =$E11/$D11
A12: Vêtement, livre, bijou fantaisie | B12: C2 | C12: < 25 000 | D12: =IF($B12="C5", ROUND(MAX(Parametres!$B$12, MIN(Parametres!$B$13, Parametres!$B$11*1500000)), 0), VLOOKUP($B12,Parametres!$A$4:$C$8,2,0)) | E12: =IF($B12="C5", ROUND($D12*Parametres!$B$14,0), VLOOKUP($B12,Parametres!$A$4:$C$8,3,0)) | F12: =$D12-$E12 | G12: =$E12/$D12
A13: Téléphone entrée / milieu de gamme (Tecno Pop, Galaxy A16–A36) | B13: C3 | C13: 60 000 – 160 000 | D13: =IF($B13="C5", ROUND(MAX(Parametres!$B$12, MIN(Parametres!$B$13, Parametres!$B$11*1500000)), 0), VLOOKUP($B13,Parametres!$A$4:$C$8,2,0)) | E13: =IF($B13="C5", ROUND($D13*Parametres!$B$14,0), VLOOKUP($B13,Parametres!$A$4:$C$8,3,0)) | F13: =$D13-$E13 | G13: =$E13/$D13 | H13: Prix boutiques N'Djamena 2025–2026
A14: Écouteurs, montre connectée | B14: C3 | C14: 15 000 – 250 000 | D14: =IF($B14="C5", ROUND(MAX(Parametres!$B$12, MIN(Parametres!$B$13, Parametres!$B$11*1500000)), 0), VLOOKUP($B14,Parametres!$A$4:$C$8,2,0)) | E14: =IF($B14="C5", ROUND($D14*Parametres!$B$14,0), VLOOKUP($B14,Parametres!$A$4:$C$8,3,0)) | F14: =$D14-$E14 | G14: =$E14/$D14
A15: Ordinateur portable, tablette | B15: C3 | C15: 60 000 – 600 000 | D15: =IF($B15="C5", ROUND(MAX(Parametres!$B$12, MIN(Parametres!$B$13, Parametres!$B$11*1500000)), 0), VLOOKUP($B15,Parametres!$A$4:$C$8,2,0)) | E15: =IF($B15="C5", ROUND($D15*Parametres!$B$14,0), VLOOKUP($B15,Parametres!$A$4:$C$8,3,0)) | F15: =$D15-$E15 | G15: =$E15/$D15 | H15: Dès 60 000–180 000 observés à N'Djamena
A16: Appareil photo grand public | B16: C3 | C16: 80 000 – 500 000 | D16: =IF($B16="C5", ROUND(MAX(Parametres!$B$12, MIN(Parametres!$B$13, Parametres!$B$11*1500000)), 0), VLOOKUP($B16,Parametres!$A$4:$C$8,2,0)) | E16: =IF($B16="C5", ROUND($D16*Parametres!$B$14,0), VLOOKUP($B16,Parametres!$A$4:$C$8,3,0)) | F16: =$D16-$E16 | G16: =$E16/$D16
A17: Vélo, trottinette | B17: C3 | C17: 50 000 – 300 000 | D17: =IF($B17="C5", ROUND(MAX(Parametres!$B$12, MIN(Parametres!$B$13, Parametres!$B$11*1500000)), 0), VLOOKUP($B17,Parametres!$A$4:$C$8,2,0)) | E17: =IF($B17="C5", ROUND($D17*Parametres!$B$14,0), VLOOKUP($B17,Parametres!$A$4:$C$8,3,0)) | F17: =$D17-$E17 | G17: =$E17/$D17 | H17: Proposition — non listé dans le plan v2
A18: Smartphone haut de gamme (iPhone 16, POCO X7 Pro) | B18: C4 | C18: 200 000 – 1 000 000 | D18: =IF($B18="C5", ROUND(MAX(Parametres!$B$12, MIN(Parametres!$B$13, Parametres!$B$11*1500000)), 0), VLOOKUP($B18,Parametres!$A$4:$C$8,2,0)) | E18: =IF($B18="C5", ROUND($D18*Parametres!$B$14,0), VLOOKUP($B18,Parametres!$A$4:$C$8,3,0)) | F18: =$D18-$E18 | G18: =$E18/$D18 | H18: iPhone 16 = 704 000 FCFA observé
A19: Sac / article de marque | B19: C4 | C19: 150 000 – 1 000 000 | D19: =IF($B19="C5", ROUND(MAX(Parametres!$B$12, MIN(Parametres!$B$13, Parametres!$B$11*1500000)), 0), VLOOKUP($B19,Parametres!$A$4:$C$8,2,0)) | E19: =IF($B19="C5", ROUND($D19*Parametres!$B$14,0), VLOOKUP($B19,Parametres!$A$4:$C$8,3,0)) | F19: =$D19-$E19 | G19: =$E19/$D19
A20: Bijoux précieux (or, pierres) | B20: C4 | C20: 100 000 – 1 000 000 | D20: =IF($B20="C5", ROUND(MAX(Parametres!$B$12, MIN(Parametres!$B$13, Parametres!$B$11*1500000)), 0), VLOOKUP($B20,Parametres!$A$4:$C$8,2,0)) | E20: =IF($B20="C5", ROUND($D20*Parametres!$B$14,0), VLOOKUP($B20,Parametres!$A$4:$C$8,3,0)) | F20: =$D20-$E20 | G20: =$E20/$D20
A21: Instrument de musique, matériel professionnel | B21: C4 | C21: 200 000 – 1 000 000 | D21: =IF($B21="C5", ROUND(MAX(Parametres!$B$12, MIN(Parametres!$B$13, Parametres!$B$11*1500000)), 0), VLOOKUP($B21,Parametres!$A$4:$C$8,2,0)) | E21: =IF($B21="C5", ROUND($D21*Parametres!$B$14,0), VLOOKUP($B21,Parametres!$A$4:$C$8,3,0)) | F21: =$D21-$E21 | G21: =$E21/$D21
A22: Animal de compagnie | B22: C4 | C22: valeur sentimentale (20 000 – 500 000) | D22: =IF($B22="C5", ROUND(MAX(Parametres!$B$12, MIN(Parametres!$B$13, Parametres!$B$11*1500000)), 0), VLOOKUP($B22,Parametres!$A$4:$C$8,2,0)) | E22: =IF($B22="C5", ROUND($D22*Parametres!$B$14,0), VLOOKUP($B22,Parametres!$A$4:$C$8,3,0)) | F22: =$D22-$E22 | G22: =$E22/$D22 | H22: Proposition
A23: Objet de très grande valeur, véhicule, lot d'entreprise | B23: C5 | C23: > 1 000 000 | D23: =IF($B23="C5", ROUND(MAX(Parametres!$B$12, MIN(Parametres!$B$13, Parametres!$B$11*1500000)), 0), VLOOKUP($B23,Parametres!$A$4:$C$8,2,0)) | E23: =IF($B23="C5", ROUND($D23*Parametres!$B$14,0), VLOOKUP($B23,Parametres!$A$4:$C$8,3,0)) | F23: =$D23-$E23 | G23: =$E23/$D23 | H23: 1 % de la valeur déclarée (ex. 1 500 000 FCFA) ; plancher 5 000 / plafond 25 000. Les flagships ~1 M FCFA basculent en C5
A25: Options (onglet Parametres) : traitement urgent +50 % ; conciergerie documents 1 000 FCFA ; livraison urbaine défaut 2 500 FCFA (proxy — devis partenaires Nimvi Express, Kimre, Speed Delivery). Commission affichée HT — TVA paramétrable.

Sheet Calibrage marché
A1: Calibrage sur les prix observés — N'Djamena (recherche du 21/09/2026)
A2: « Vérifié » = donnée tchadienne trouvée en ligne ce tour. « Proxy » = comparable utilisé faute de tarif publié localement. Toutes les URLs sont cliquables (colonne Source).
A4: Poste | B4: Donnée observée (FCFA) | C4: Source (lien) | D4: Date | E4: Type | F4: Implication pour la grille
A5: Carte d'identité nationale (coût/renouvellement) | B5: 5 000 – 10 000 (tarif officiel ; projet ANATS à 5 000 ; fin de la gratuité le 02/08/2023) | C5: VOA Afrique — https://www.voaafrique.com/a/le-prix-des-cartes-d-identite-fait-grogner-les-tchadiens/3935774.html ; Alwihda Info — https://www.alwihdainfo.com/Tchad-le-cout-des-titres-securises-va-baisser_a81674.html ; Journal du Tchad — https://journaldutchad.com/tchad-fin-de-la-gratuite-de-la-carte-didentite-nationale/ | D5: 2017 ; s.d. ; 08/2023 | E5: Tchad — vérifié | F5: Frais C1 300 ≈ 3–6 % du coût de remplacement → proportionné, non dissuasif
A6: Passeport biométrique | B6: 60 000 | C6: Wikipédia — Passeport tchadien — https://fr.wikipedia.org/wiki/Passeport_tchadien ; Alwihda Info (centre de Bongor) — https://www.alwihdainfo.com/Tchad-ouverture-d-un-centre-de-delivrance-de-titres-securises-a-Bongor_a120987.html | D6: s.d. | E6: Tchad — vérifié | F6: Perte très coûteuse → C1 justifié + option conciergerie pertinente
A7: Permis de conduire | B7: 25 000 (retrait) ; parcours auto-école ≈ 59 500 | C7: Alwihda Info (Bongor) — https://www.alwihdainfo.com/Tchad-ouverture-d-un-centre-de-delivrance-de-titres-securises-a-Bongor_a120987.html ; Alwihda / Facebook (promo Yoka) — https://www.facebook.com/Alwihda/posts/10159193695616782/ | D7: s.d. | E7: Tchad — vérifié | F7: Confirme la classe C1 documents
A8: SMIG mensuel | B8: 60 000 / mois (≈ 2 300 / jour ouvré) | C8: Africa HR — https://africa-hr.com/fr/blog/salary-standards-across-54-african-countries/ ; Africa Paie RH — https://africapaierh.com/juridique/le-smig-en-afrique-central/ | D8: en vigueur | E8: Tchad — vérifié | F8: C1 300 ≈ 0,5 % d'un SMIG ; frais max C4 3 000 ≈ 5 % d'un SMIG → accessible
A9: Repas / petites dépenses courantes | B9: Repas restaurant bon marché 5 000 ; petit-déj 500 – 2 000 ; coro de riz 1 300 | C9: Numbeo N'Djamena — https://fr.numbeo.com/co%C3%BBt-de-la-vie/ville/N%27Djamena-Tchad ; Le Mag Voyage — https://www.lemagvoyage.fr/tchad/budget-voyage-tchad/ ; Tchad Infos — https://tchadinfos.com/2023/08/17/societe-hausse-considerable-des-prix-des-denrees-de-premiere-necessite-a-ndjamena/ | D9: 09/2026 ; s.d. ; 08/2023 | E9: Tchad — vérifié | F9: Étalon « petite dépense » : C2 700 ≈ un petit-déj ; C3 1 200 reste modéré
A10: Téléphones entrée / milieu de gamme | B10: Tecno Pop 60 000 – 75 000 ; Galaxy A16 80 000 ; A17 100 000 ; A26 130 000 ; A36 160 000 | C10: Khouma et Frères — https://www.khoumaetfreres.com/ ; Smart Boutique Chad — https://www.facebook.com/SMARTB.SBC/ | D10: 2025 – 2026 | E10: Tchad — vérifié | F10: Frais C3 1 200 ≈ 0,7 – 2 % de la valeur de l'objet
A11: Smartphones haut de gamme | B11: S21 Ultra (occasion) 180 000 ; POCO X7 Pro 215 000 ; iPhone 16 704 000 | C11: Boutique Souroubé — https://www.tiktok.com/@boutiquesouroube/video/7426342483329682693 ; HADIMI Tchad — https://www.hadimi.td/collections/telephone-tablettes | D11: 2025 – 2026 | E11: Tchad — vérifié | F11: Frontière C3→C4 ≈ 200 000 de valeur d'objet
A12: Flagships (haut de gamme extrême) | B12: Samsung S25 Ultra ≈ 1 000 000 – 1 200 000 (flambée 03/2026) | C12: Tchad Infos — https://tchadinfos.com/2026/03/17/ndjamena-les-telephones-deviennent-rares-et-hors-de-prix-a-cause-de-la-guerre-au-moyen-orient/ | D12: 17/03/2026 | E12: Tchad — vérifié | F12: Seuil C5 (> 1 000 000) cohérent avec le marché réel ; fee 1 % s'applique
A13: Ordinateurs portables | B13: Dès 60 000 (promo) ; Lenovo i5 180 000 ; HP 144 000 – 390 000 ; HP Victus 660 000 ; Dell 680 000 | C13: Lalekou Informatique — https://www.facebook.com/lalekouinformatiqueshop/ ; Tchad City Computers — https://www.facebook.com/p/Tchad-city-computers-nouvelle-g%C3%A9n%C3%A9ration-100088890590050/ ; Chine Express Afrique — https://chine-express-afrique.com/ordinateurs-portables/ ; AWALKM — http://www.awalkm.com/product-categories/informatique | D13: 2025 – 2026 | E13: Tchad — vérifié | F13: Couvre la bascule C3 → C4 (600 000)
A14: Airtel Money Tchad (retrait / envoi) | B14: ≤ 3 % du montant (plafond annoncé par l'opérateur) | C14: Airtel Tchad (officiel) — https://www.facebook.com/AirtelTchad/posts/1030231869129123 ; Airtel Tchad — frais — https://www.airtel.td/airtel_money | D14: 2025 – 2026 | E14: Tchad — vérifié | F14: Coût d'encaissement 9 – 90 FCFA par paiement Liguita → négligeable vs commission
A15: Moov Money Tchad | B15: Transfert 0,70 % (promo) ; retrait 3 % ; Money Xpress 5 % | C15: Moov Africa Tchad — https://www.linkedin.com/posts/tigotchad_moovmoney-moovafricatchad-activity-7361412429085384705-RhAu | D15: 2025 – 2026 | E15: Tchad — vérifié | F15: Négocier un tarif marchand < retrait ; prévoir plusieurs providers (plan §31)
... A19: Duplication de clés | B19: ≈ 2 000 – 5 000 | C19: Proxy régional (aucun tarif local publié) | D19: — | E19: PROXY régional | F19: C2 700 ≈ 15 – 35 % du coût de duplication → cohérent

Sheet Parametres
A1: Hypothèses & paramètres — cellules modifiables (les formules se recalculent)
A3: Classe | B3: Frais de base (FCFA) | C3: Récompense trouveur (FCFA)
A4: C1 | B4: 300 | C4: 100
A5: C2 | B5: 700 | C5: 250
A6: C3 | B6: 1200 | C6: 400
A7: C4 | B7: 3000 | C7: 900
A8: C5 | B8: 0.01 | C8: 0.3
A10: Paramètres C5 (cas spéciaux)
A11: Taux sur la valeur déclarée | B11: 0.01
A12: Plancher (FCFA) | B12: 5000
A13: Plafond (FCFA) | B13: 25000
A14: Part trouveur (C5) | B14: 0.3
A16: Options
A17: Traitement urgent — supplément (% des frais de base) | B17: 0.5
A18: Conciergerie documents (FCFA) | B18: 1000
A19: Livraison urbaine N'Djamena — défaut (proxy, sur devis partenaires) | B19: 2500
A21: TVA
A22: Taux de TVA (Tchad — à valider avec un comptable) | B22: 0.18
A23: La commission Liguita est affichée hors taxes ; appliquer la TVA le cas échéant.
A25: Calibrage 09/2026 : les frais C1–C5 résistent au test du marché (détail onglet « Calibrage marché »). Répartition cible : trouveur ≈ 1/3 des frais (C1–C4) ; 30/70 (C5).

Sheet Exemples chiffrés
A1: Exemples chiffrés — scénarios de mise en relation
A2: Toutes les cellules se recalculent depuis l'onglet Parametres. La « valeur déclarée » de la ligne C5 est modifiable.
A4: Scénario | B4: Classe | C4: Valeur déclarée (si C5) | D4: Frais de base | E4: Option | F4: Supplément option | G4: Total à payer | H4: Récompense trouveur | I4: Commission Liguita
A5: CNI retrouvée — mise en relation standard | B5: C1 | D5: =IF($B5="C5", ROUND(MAX(Parametres!$B$12, MIN(Parametres!$B$13, Parametres!$B$11*N($C5))),0), VLOOKUP($B5,Parametres!$A$4:$C$8,2,0)) | E5: — | F5: =IF($E5="Urgent", ROUND($D5*Parametres!$B$17,0), IF($E5="Conciergerie", Parametres!$B$18, IF($E5="Livraison", Parametres!$B$19, 0))) | G5: =$D5+$F5 | H5: =IF($B5="C5", ROUND($D5*Parametres!$B$14,0), VLOOKUP($B5,Parametres!$A$4:$C$8,3,0)) | I5: =$G5-$H5
A6: CNI — traitement urgent | B6: C1 | D6: =IF($B6="C5", ROUND(MAX(Parametres!$B$12, MIN(Parametres!$B$13, Parametres!$B$11*N($C6))),0), VLOOKUP($B6,Parametres!$A$4:$C$8,2,0)) | E6: Urgent | F6: =IF($E6="Urgent", ROUND($D6*Parametres!$B$17,0), IF($E6="Conciergerie", Parametres!$B$18, IF($E6="Livraison", Parametres!$B$19, 0))) | G6: =$D6+$F6 | H6: =IF($B6="C5", ROUND($D6*Parametres!$B$14,0), VLOOKUP($B6,Parametres!$A$4:$C$8,3,0)) | I6: =$G6-$H6
A7: Téléphone — mise en relation standard | B7: C3 | D7: =IF($B7="C5", ROUND(MAX(Parametres!$B$12, MIN(Parametres!$B$13, Parametres!$B$11*N($C7))),0), VLOOKUP($B7,Parametres!$A$4:$C$8,2,0)) | E7: — | F7: =IF($E7="Urgent", ROUND($D7*Parametres!$B$17,0), IF($E7="Conciergerie", Parametres!$B$18, IF($E7="Livraison", Parametres!$B$19, 0))) | G7: =$D7+$F7 | H7: =IF($B7="C5", ROUND($D7*Parametres!$B$14,0), VLOOKUP($B7,Parametres!$A$4:$C$8,3,0)) | I7: =$G7-$H7
A8: Téléphone — traitement urgent | B8: C3 | D8: =IF($B8="C5", ROUND(MAX(Parametres!$B$12, MIN(Parametres!$B$13, Parametres!$B$11*N($C8))),0), VLOOKUP($B8,Parametres!$A$4:$C$8,2,0)) | E8: Urgent | F8: =IF($E8="Urgent", ROUND($D8*Parametres!$B$17,0), IF($E8="Conciergerie", Parametres!$B$18, IF($E8="Livraison", Parametres!$B$19, 0))) | G8: =$D8+$F8 | H8: =IF($B8="C5", ROUND($D8*Parametres!$B$14,0), VLOOKUP($B8,Parametres!$A$4:$C$8,3,0)) | I8: =$G8-$H8
A9: Ordinateur + conciergerie documents | B9: C3 | D9: =IF($B9="C5", ROUND(MAX(Parametres!$B$12, MIN(Parametres!$B$13, Parametres!$B$11*N($C9))),0), VLOOKUP($B9,Parametres!$A$4:$C$8,2,0)) | E9: Conciergerie | F9: =IF($E9="Urgent", ROUND($D9*Parametres!$B$17,0), IF($E9="Conciergerie", Parametres!$B$18, IF($E9="Livraison", Parametres!$B$19, 0))) | G9: =$D9+$F9 | H9: =IF($B9="C5", ROUND($D9*Parametres!$B$14,0), VLOOKUP($B9,Parametres!$A$4:$C$8,3,0)) | I9: =$G9-$H9
A10: Téléphone + livraison urbaine (proxy 2 500) | B10: C3 | D10: =IF($B10="C5", ROUND(MAX(Parametres!$B$12, MIN(Parametres!$B$13, Parametres!$B$11*N($C10))),0), VLOOKUP($B10,Parametres!$A$4:$C$8,2,0)) | E10: Livraison | F10: =IF($E10="Urgent", ROUND($D10*Parametres!$B$17,0), IF($E10="Conciergerie", Parametres!$B$18, IF($E10="Livraison", Parametres!$B$19, 0))) | G10: =$D10+$F10 | H10: =IF($B10="C5", ROUND($D10*Parametres!$B$14,0), VLOOKUP($B10,Parametres!$A$4:$C$8,3,0)) | I10: =$G10-$H10
A11: Sac de marque | B11: C4 | D11: =IF($B11="C5", ROUND(MAX(Parametres!$B$12, MIN(Parametres!$B$13, Parametres!$B$11*N($C11))),0), VLOOKUP($B11,Parametres!$A$4:$C$8,2,0)) | E11: — | F11: =IF($E11="Urgent", ROUND($D11*Parametres!$B$17,0), IF($E11="Conciergerie", Parametres!$B$18, IF($E11="Livraison", Parametres!$B$19, 0))) | G11: =$D11+$F11 | H11: =IF($B11="C5", ROUND($D11*Parametres!$B$14,0), VLOOKUP($B11,Parametres!$A$4:$C$8,3,0)) | I11: =$G11-$H11
A12: Lot d'entreprise — valeur déclarée 1 500 000 | B12: C5 | C12: 1500000 | D12: =IF($B12="C5", ROUND(MAX(Parametres!$B$12, MIN(Parametres!$B$13, Parametres!$B$11*N($C12))),0), VLOOKUP($B12,Parametres!$A$4:$C$8,2,0)) | E12: — | F12: =IF($E12="Urgent", ROUND($D12*Parametres!$B$17,0), IF($E12="Conciergerie", Parametres!$B$18, IF($E12="Livraison", Parametres!$B$19, 0))) | G12: =$D12+$F12 | H12: =IF($B12="C5", ROUND($D12*Parametres!$B$14,0), VLOOKUP($B12,Parametres!$A$4:$C$8,3,0)) | I12: =$G12-$H12
A14: Lecture : le supplément d'urgence alimente la commission Liguita (proposition — la récompense du trouveur reste celle de sa classe) ; la livraison est reversée au partenaire (proxy 2 500, sur devis). Montant toujours affiché avant paiement et figé dans un devis (price_quote).
